cloudmesh_test-4.3.2-py3.9-nspkg.pth
cloudmesh/test/CloudmeshTest.py
cloudmesh/test/__init__.py
cloudmesh/test/__version__.py
cloudmesh/test/command/__init__.py
cloudmesh/test/command/test.py
cloudmesh_test-4.3.2.dist-info/LICENSE
cloudmesh_test-4.3.2.dist-info/METADATA
cloudmesh_test-4.3.2.dist-info/WHEEL
cloudmesh_test-4.3.2.dist-info/namespace_packages.txt
cloudmesh_test-4.3.2.dist-info/top_level.txt
cloudmesh_test-4.3.2.dist-info/RECORD
