Metadata-Version: 2.1
Name: cloudmesh-test
Version: 4.3.2
Summary: A command to do a simple test to identify potential flaws before using cloudmesh
Home-page: https://github.com/cloudmesh/cloudmesh-test
Author: Gregor von Laszewski
Author-email: laszewski@gmail.com
License: Apache 2.0
Platform: UNKNOWN
Classifier: Development Status :: 5 - Production/Stable
Classifier: Environment :: Console
Classifier: Environment :: Other Environment
Classifier: Environment :: Plugins
Classifier: Intended Audience :: Information Technology
Classifier: Intended Audience :: Developers
Classifier: Intended Audience :: Education
Classifier: Intended Audience :: Science/Research
Classifier: Intended Audience :: System Administrators
Classifier: License :: OSI Approved :: Apache Software License
Classifier: Natural Language :: English
Classifier: Operating System :: OS Independent
Classifier: Operating System :: MacOS :: MacOS X
Classifier: Operating System :: POSIX :: Linux
Classifier: Operating System :: Microsoft :: Windows :: Windows 10
Classifier: Programming Language :: Python
Classifier: Programming Language :: Python :: 3
Classifier: Programming Language :: Python :: 3.7
Classifier: Programming Language :: Python :: 3.8
Classifier: Programming Language :: Python :: 3.9
Classifier: Topic :: Internet
Classifier: Topic :: Scientific/Engineering
Classifier: Topic :: Software Development :: Libraries
Classifier: Topic :: Software Development :: User Interfaces
Classifier: Topic :: System
Classifier: Topic :: System :: Distributed Computing
Classifier: Topic :: System :: Shells
Classifier: Topic :: Utilities
Requires-Dist: psutil
Requires-Dist: yamllint
Requires-Dist: cloudmesh-common
Requires-Dist: cloudmesh-cmd5
Requires-Dist: cloudmesh-abstract
Requires-Dist: cloudmesh-configuration
